flexvalue/__init__.py
flexvalue/__version__.py
flexvalue/cli.py
flexvalue/config.py
flexvalue/db.py
flexvalue/flexvalue.py
flexvalue/settings.py
flexvalue/sql/create_elec_av_cost.sql
flexvalue/sql/create_elec_load_shape.sql
flexvalue/sql/create_gas_av_cost.sql
flexvalue/sql/create_project_info.sql
flexvalue/sql/create_therms_profile.sql
flexvalue/sql/elec_av_costs_index.sql
flexvalue/sql/elec_load_shape_index.sql
flexvalue/sql/gas_av_costs_index.sql
flexvalue/sql/postgres_indexes.sql
flexvalue/sql/project_info_dates_index.sql
flexvalue/sql/project_info_index.sql
flexvalue/sql/therm_profile_index.sql
flexvalue/templates/bq_create_elec_load_shape.sql
flexvalue/templates/bq_create_therms_profile.sql
flexvalue/templates/bq_populate_elec_load_shape.sql
flexvalue/templates/bq_populate_metered_load_shape.sql
flexvalue/templates/bq_populate_therms_profile.sql
flexvalue/templates/calculation.sql
flexvalue/templates/elec_calculation.sql
flexvalue/templates/gas_calculation.sql
flexvalue/templates/get_project_info.sql
flexvalue/templates/get_therms_profiles.sql
flexvalue/templates/load_elec_av_costs.sql
flexvalue/templates/load_elec_load_shape.sql
flexvalue/templates/load_gas_av_costs.sql
flexvalue/templates/load_project_info.sql
flexvalue/templates/load_therms_profiles.sql
flexvalue-2.0.8.data/data/sql/create_elec_av_cost.sql
flexvalue-2.0.8.data/data/sql/create_elec_load_shape.sql
flexvalue-2.0.8.data/data/sql/create_gas_av_cost.sql
flexvalue-2.0.8.data/data/sql/create_project_info.sql
flexvalue-2.0.8.data/data/sql/create_therms_profile.sql
flexvalue-2.0.8.data/data/sql/elec_av_costs_index.sql
flexvalue-2.0.8.data/data/sql/elec_load_shape_index.sql
flexvalue-2.0.8.data/data/sql/gas_av_costs_index.sql
flexvalue-2.0.8.data/data/sql/postgres_indexes.sql
flexvalue-2.0.8.data/data/sql/project_info_dates_index.sql
flexvalue-2.0.8.data/data/sql/project_info_index.sql
flexvalue-2.0.8.data/data/sql/therm_profile_index.sql
flexvalue-2.0.8.dist-info/LICENSE.md
flexvalue-2.0.8.dist-info/METADATA
flexvalue-2.0.8.dist-info/WHEEL
flexvalue-2.0.8.dist-info/entry_points.txt
flexvalue-2.0.8.dist-info/top_level.txt
flexvalue-2.0.8.dist-info/RECORD
