Metadata-Version: 2.1
Name: flexvalue
Version: 2.0.8
Summary: FLEXvalue: a tool for calculating avoided costs
Home-page: http://github.com/recurve-methods/flexvalue
Author: Recurve Analytics, Inc.
Author-email: support@recurve.com
License: Apache 2.0
Platform: UNKNOWN
Classifier: License :: OSI Approved :: Apache Software License
Classifier: Programming Language :: Python
Classifier: Programming Language :: Python :: 3
Classifier: Programming Language :: Python :: 3.4
Classifier: Programming Language :: Python :: 3.5
Classifier: Programming Language :: Python :: 3.6
Classifier: Programming Language :: Python :: 3.7
Requires-Dist: click (>=8.0.0)
Requires-Dist: toml (>=0.10.2)
Requires-Dist: sqlalchemy (==2.0)
Requires-Dist: jinja2 (==3.0.3)
Requires-Dist: psycopg[binary] (==3.1.8)
Requires-Dist: google-cloud-bigquery (>=2.34.3)
